tcrsep/__init__.py
tcrsep/dataset.py
tcrsep/estimator.py
tcrsep/eval.py
tcrsep/pgen.py
tcrsep/sharing_analysis.py
tcrsep/test.py
tcrsep/utils.py
tcrsep/gene_segment/J_segment_sequences.fasta
tcrsep/gene_segment/V_segment_sequences.fasta
tcrsep/models/embedding_model/CDR3vec/config.json
tcrsep/models/embedding_model/CDR3vec/pytorch_model.bin
tcrsep/models/embedding_model/TCR2vec/config.json
tcrsep/models/embedding_model/TCR2vec/pytorch_model.bin
tcrsep/models/generation_model/CMV_whole/J_gene_CDR3_anchors.csv
tcrsep/models/generation_model/CMV_whole/V_gene_CDR3_anchors.csv
tcrsep/models/generation_model/CMV_whole/genomicDs.fasta
tcrsep/models/generation_model/CMV_whole/genomicJs.fasta
tcrsep/models/generation_model/CMV_whole/genomicVs.fasta
tcrsep/models/generation_model/CMV_whole/model_marginals.txt
tcrsep/models/generation_model/CMV_whole/model_params.txt
tcrsep/models/generation_model/COVID/J_gene_CDR3_anchors.csv
tcrsep/models/generation_model/COVID/V_gene_CDR3_anchors.csv
tcrsep/models/generation_model/COVID/genomicDs.fasta
tcrsep/models/generation_model/COVID/genomicJs.fasta
tcrsep/models/generation_model/COVID/genomicVs.fasta
tcrsep/models/generation_model/COVID/model_marginals.txt
tcrsep/models/generation_model/COVID/model_params.txt
tcrsep/models/selection_model/CMV/args.json
tcrsep/models/selection_model/CMV/tcrsep.pth
tcrsep/models/selection_model/COVID/args.json
tcrsep/models/selection_model/COVID/tcrsep.pth
tcrsep-1.3.1.data/data/LICENSE
tcrsep-1.3.1.data/data/README.md
tcrsep-1.3.1.dist-info/LICENSE
tcrsep-1.3.1.dist-info/METADATA
tcrsep-1.3.1.dist-info/WHEEL
tcrsep-1.3.1.dist-info/top_level.txt
tcrsep-1.3.1.dist-info/RECORD
