Metadata-Version: 2.1
Name: tcrsep
Version: 1.3.1
Summary: Selection model for immune receptor repertoires
Home-page: https://github.com/jiangdada1221/TCRsep
Author: Yuepeng Jiang
Author-email: jiangdada12344321@gmail.com
License: GPLv3
Platform: UNKNOWN
Classifier: Development Status :: 3 - Alpha
Classifier: Intended Audience :: Developers
Classifier: Intended Audience :: Healthcare Industry
Classifier: Intended Audience :: Science/Research
Classifier: Topic :: Scientific/Engineering :: Bio-Informatics
Classifier: Topic :: Scientific/Engineering :: Artificial Intelligence
Classifier: Topic :: Scientific/Engineering :: Medical Science Apps.
Classifier: License :: OSI Approved :: GNU General Public License v3 (GPLv3)
Classifier: Natural Language :: English
Classifier: Programming Language :: Python :: 3
Requires-Python: >=3.6
License-File: LICENSE
Requires-Dist: numpy
Requires-Dist: torch (>=1.5.0)
Requires-Dist: tqdm
Requires-Dist: pandas
Requires-Dist: scikit-learn
Requires-Dist: Scipy
Requires-Dist: tcr2vec
Requires-Dist: olga
Requires-Dist: biopython
Requires-Dist: sympy
Requires-Dist: matplotlib
